pytosql/__init__.py
pytosql-0.1.0.dist-info/AUTHORS
pytosql-0.1.0.dist-info/METADATA
pytosql-0.1.0.dist-info/WHEEL
pytosql-0.1.0.dist-info/pbr.json
pytosql-0.1.0.dist-info/top_level.txt
pytosql-0.1.0.dist-info/RECORD
